{
  "uuid": "7113567e-c974-4c1c-8544-090786e16a5e",
  "shortname": "7113567e",
  "is_active": true,  "owner_shortname": "dmart",
  "author_locator": { "type": "content",
    "uuid": "15d34541-3bed-4775-887b-b73a43598f8e",
    "shortname": "فيصل_الوليدي",
    "subpath": "profiles/",
    "space_name": "maqola",
    "resource_type": "locator",
    "tags": [],
    "typename": "user"
  },
  "resource_type": "reaction",
  "tags": [],
  "created_at": "2020-09-18T19:45:06+03:00",
  "attributes": {
    "old_id": 185,
    "old_entry_id": 610
  },
  "language": "en",
  "type": "like"
}
