{
  "uuid": "7eb9de0f-98e4-421a-b4ca-5839ab98c271",
  "shortname": "جمال_عبد_الناصر",
  "is_active": true,  "owner_shortname": "dmart",
  "displayname":{"ar":"جمال عبد الناصر"},
  "payload": {
    "content_type": "html",
    "checksum": "sha1:4ad9af5839ec69235754bdd70c1079010cf7c400",
    "bytesize": 36,
    "body": "هو جمال عبد الناصر :)"
  },
  "author_locator": { "type": "content",
    "uuid": "55b5b9e8-d80a-4fca-be27-7dd0eaf5a660",
    "shortname": "مجهول",
    "subpath": "profiles/",
    "space_name": "maqola",
    "resource_type": "locator",
    "tags": [],
    "typename": "user"
  },
  "resource_type": "reply",
  "tags": [],
  "created_at": "2011-08-31T23:13:31Z",
  "attributes": {
    "old_id": 522,
    "old_entry_id": 514
  },
  "language": "ar"
}
