{
  "uuid": "6b405d98-28cf-49ef-bbbf-8ad7ca8e47c2",
  "shortname": "6b405d98",
  "is_active": true,  "owner_shortname": "dmart",
  "author_locator": { "type": "content",
    "uuid": "3783e309-7c11-4fd3-9913-73ee7960e4a7",
    "shortname": "hani",
    "subpath": "profiles/",
    "space_name": "maqola",
    "resource_type": "locator",
    "tags": [],
    "typename": "user"
  },
  "resource_type": "reaction",
  "tags": [],
  "created_at": "2020-09-18T19:45:07+03:00",
  "attributes": {
    "old_id": 354,
    "old_entry_id": 830
  },
  "language": "en",
  "type": "like"
}
