{
  "uuid": "c0018396-bbc7-48ad-8e73-23b219e8a764",
  "shortname": "عبد_الملك_والحجاج_وعروة_ابن_الزبير_",
  "is_active": true,  "owner_shortname": "dmart",
  "displayname":{"ar":"عبد الملك والحجاج وعروة ابن الزبير:"},
  "payload": {
    "content_type": "html",
    "checksum": "sha1:82de53aa51d683e4ee7f479e4887226d89835d94",
    "bytesize": 3275,
    "body": "<p>كان عروة بن الزبير عاملا على اليمن لعبد الملك بن مروان ، فاتصل به أن الحجاج مجمع على مطالبته بالأموال التي بيده وعزله عن عمله ؛ ففر إلى عبد الملك وعاذ به تخوّفا من الحجاج واستدفاعا لضرره وشرّه ؛ فلما بلغ ذلك الحجاج كتب إلى عبد الملك بن مروان : \" أما بعد فإن لواذ المعترضين بك ، وحلول الجانحين إلى المكث بساحتك ، واستلانتهم دمث أخلاقك وسعة عفوك ، كالعارض المبرق لأعدائه لا يعدم له شائما ، رجاء استمالة عفوك ؛ وإذا أدني الناس بالصفح عن الجرائم ، كان ذلك تمرينا لهم على إضاعة الحقوق مع كل وال والناس عبيد العصا ، هم على الشدة أشدّ استباقا منهم على اللين ، ولنا قبل عروة بن الزبير مال من مال الله ، وفي استخراجه منه قطع لطمع غيره ، فليبعث به أمير المؤمنين إن رأى ذلك ، والسلام . فلما قرأ الكتاب ، بعث إلى عروة ثم قال له : إن كتاب الحجاج قد ورد فيك ، وقد أبى إلا إشخاصك إليه . ثم قال لرسول الحجاج : شأنك به . فالتفت إليه عروة مقبلا عليه ، وقال : أما والله ما ذلّ وخزي من مات ، ولكن ذل وخزي من ملكتموه ؛ والله لئن كان الملك بجواز الأمر ونفاذ النهي ، إن الحجاج لسلطان عليك ، ينفذ أموره دون أمورك ؛ إنك لتريد الأمر يزينك عاجله ويبقى لك أكرومة آجله، فيجذبك عنه ويلقاه دونك ، ليتولى من ذلك الحكم فيه ، فيحظى بشرف عفو إن كان ، أو يجرم عقوبة إن كانت ، وما حاربك من حاربك إلا على أمر هذا بعضه . قال : فنظر في كتاب الحجاج مرة ورفع بصره إلى عروة تارة ، ثم دعا بدواة وقرطاس فكتب إليه :</p><p>أما بعد ، فإن أمير المؤمنين رآك مع ثقته بنصيحتك ، خابطا في السياسة خبط عشواء الليل ؛ فإنّ رأيك الذي يسولّ لك أن الناس عبيد العصا ، هو الذي أخرج رجالات العرب إلى الوثوب عليك ، وإذا أحرجت العامة بعنف السياسة ، كانوا أوشك وثوبا عليك عند الفرصة ، ثم لا يلتفتون إلى ضلال الداعي ولا هداه ، إذا رجوا بذلك إدراك الثأر منك ؛ وقد وليت العراق قبلك ساسة ، وهم يومئذ أحمى أنوفا ، وأقرب من عمياء الجاهلية ، وكانوا عليهم أصلح منك عليهم ، وللشدة واللين أهلون ، والإفراط في العفو أفضل من الإفراط في العقوبة ، والسلام .</p><p>من كتاب العقد الفريد لابن عبد ربه الأندلسي \" 246 هـ - 328 هـ \"</p>"
  },
  "author_locator": { "type": "content",
    "uuid": "c2e78c7a-a794-4282-b1ca-fef8f39150a0",
    "shortname": "مجهول",
    "subpath": "/profiles/",
    "space_name": "maqola",
    "resource_type": "locator",
    "tags": [],
    "typename": "biography"
  },
  "editor_locator": {
    "uuid": "9f641283-758a-4071-98e9-da62c6932b1a",
    "shortname": "ياقوت_الفرزدقي",
    "subpath": "profiles/",
    "space_name": "maqola",
    "resource_type": "locator",
    "tags": [],
    "typename": "user"
  },
  "owner_uuid": "2b0e517d-14b6-4ecd-ab95-f5aae22f1b5d",
  "resource_type": "post",
  "tags": [
    "آيةٌ كَريمة",
    "إسلام",
    "حُسنُ الجواب",
    "حِكمَة",
    "ذَكاء",
    "سِياسَة",
    "شَجاعَة",
    "طُرفَة",
    "عربية",
    "فَخر",
    "فَصاحَة",
    "قِصّة",
    "لُغة عربيّة",
    "مَدح",
    "مَعروف"
  ],
  "created_at": "2015-04-12T20:39:24Z",
  "attributes": {
    "old_id": 1177
  },
  "language": "ar",
  "history": []
}
