{
  "uuid": "7778f4cd-c8a3-45ee-9fc8-1a32355f8c8f",
  "shortname": "7778f4cd",
  "is_active": true,  "owner_shortname": "dmart",
  "updated_at": "2015-02-06T13:31:06Z",
  "author_locator": { "type": "content",
    "uuid": "a007f8e4-e87f-4de9-a310-3af74f628bed",
    "shortname": "عبدالله_عيسى",
    "subpath": "profiles/",
    "space_name": "maqola",
    "resource_type": "locator",
    "tags": [],
    "typename": "user"
  },
  "resource_type": "share",
  "tags": [],
  "created_at": "2015-02-06T13:31:06Z",
  "attributes": {
    "old_id": 266,
    "old_entry_id": 997
  },
  "language": "en",
  "location": {
    "uuid": "7778f4cd-c8a3-45ee-9fc8-1a32355f8c8f",
    "shortname": "7778f4cd",
    "subpath": "posts/شعر",
    "space_name": "maqola",
    "parent_shortname": "بلاد_العرب_أوطاني",
    "resource_type": "locator",
    "tags": [],
    "typename": "share"
  }
}
